<?xml version="1.0" encoding="UTF-8"?>
<FindBugsFilter
	xmlns="https://github.com/spotbugs/filter/3.0.0"
	xmlns:xsi="http://www.w3.org/2001/XMLSchema-instance"
	xsi:schemaLocation="https://github.com/spotbugs/filter/3.0.0 https://raw.githubusercontent.com/spotbugs/spotbugs/3.1.0/spotbugs/etc/findbugsfilter.xsd">
	
	<Match>
		<Class name="ru.mystamps.web.feature.account.AddUserDbDto" />
		<Or>
			<Method name="getActivatedAt" />
			<Method name="setActivatedAt" />
			<Method name="getRegisteredAt" />
			<Method name="setRegisteredAt" />
		</Or>
		<Bug pattern="EI_EXPOSE_REP,EI_EXPOSE_REP2" />
	</Match>
	<Match>
		<Class name="ru.mystamps.web.feature.account.AddUsersActivationDbDto" />
		<Or>
			<Method name="getCreatedAt" />
			<Method name="setCreatedAt" />
		</Or>
		<Bug pattern="EI_EXPOSE_REP,EI_EXPOSE_REP2" />
	</Match>
	<Match>
		<Class name="ru.mystamps.web.feature.account.UsersActivationDto" />
		<Bug pattern="EI_EXPOSE_REP,EI_EXPOSE_REP2" />
	</Match>
	<Match>
		<Class name="ru.mystamps.web.feature.account.UsersActivationFullDto" />
		<Bug pattern="EI_EXPOSE_REP,EI_EXPOSE_REP2" />
	</Match>
	<Match>
		<Class name="ru.mystamps.web.feature.image.AddImageDataDbDto" />
		<Or>
			<Method name="getContent" />
			<Method name="setContent" />
		</Or>
		<Bug pattern="EI_EXPOSE_REP,EI_EXPOSE_REP2" />
	</Match>
	<Match>
		<Class name="ru.mystamps.web.feature.image.ImageDto" />
		<Bug pattern="EI_EXPOSE_REP,EI_EXPOSE_REP2" />
	</Match>
	<Match>
		<Class name="ru.mystamps.web.feature.report.AdminDailyReport" />
		<Or>
			<Method name="getEndDate" />
			<Method name="setEndDate" />
			<Method name="getStartDate" />
			<Method name="setStartDate" />
		</Or>
		<Bug pattern="EI_EXPOSE_REP,EI_EXPOSE_REP2" />
	</Match>
	<Match>
		<Class name="ru.mystamps.web.feature.series.sale.AddSeriesSalesForm" />
		<Or>
			<Method name="getDate" />
			<Method name="setDate" />
		</Or>
		<Bug pattern="EI_EXPOSE_REP,EI_EXPOSE_REP2" />
	</Match>
	<Match>
		<Class name="ru.mystamps.web.feature.series.sale.AddSeriesSalesDbDto" />
		<Or>
			<Method name="getDate" />
			<Method name="setDate" />
			<Method name="getCreatedAt" />
			<Method name="setCreatedAt" />
		</Or>
		<Bug pattern="EI_EXPOSE_REP,EI_EXPOSE_REP2" />
	</Match>
	<Match>
		<Class name="ru.mystamps.web.feature.series.AddSeriesDbDto" />
		<Or>
			<Method name="getCreatedAt" />
			<Method name="setCreatedAt" />
			<Method name="getUpdatedAt" />
			<Method name="setUpdatedAt" />
		</Or>
		<Bug pattern="EI_EXPOSE_REP,EI_EXPOSE_REP2" />
	</Match>
	<Match>
		<Class name="ru.mystamps.web.feature.series.PurchaseAndSaleDto" />
		<Bug pattern="EI_EXPOSE_REP,EI_EXPOSE_REP2" />
	</Match>
	<Match>
		<Class name="ru.mystamps.web.feature.series.SitemapInfoDto" />
		<Bug pattern="EI_EXPOSE_REP,EI_EXPOSE_REP2" />
	</Match>
	<Match>
		<Class name="ru.mystamps.web.feature.series.importing.UpdateImportRequestStatusDbDto" />
		<Bug pattern="EI_EXPOSE_REP,EI_EXPOSE_REP2" />
	</Match>
	<Match>
		<Class name="ru.mystamps.web.feature.series.importing.ImportSeriesDbDto" />
		<Or>
			<Method name="getRequestedAt" />
			<Method name="setRequestedAt" />
			<Method name="getUpdatedAt" />
			<Method name="setUpdatedAt" />
		</Or>
		<Bug pattern="EI_EXPOSE_REP,EI_EXPOSE_REP2" />
	</Match>
	<Match>
		<Class name="ru.mystamps.web.feature.series.importing.ImportRequestFullInfo" />
		<Bug pattern="EI_EXPOSE_REP,EI_EXPOSE_REP2" />
	</Match>
	<Match>
		<Class name="ru.mystamps.web.feature.series.importing.AddSeriesParsedDataDbDto" />
		<Or>
			<Method name="getCreatedAt" />
			<Method name="setCreatedAt" />
			<Method name="getUpdatedAt" />
			<Method name="setUpdatedAt" />
		</Or>
	</Match>
	<Match>
		<Class name="ru.mystamps.web.feature.series.importing.ImportSeriesSalesForm" />
		<Or>
			<Method name="getDate" />
			<Method name="setDate" />
		</Or>
	</Match>
	<Match>
		<Class name="ru.mystamps.web.feature.series.importing.sale.SeriesSalesParsedDataDbDto" />
		<Or>
			<Method name="getCreatedAt" />
			<Method name="setCreatedAt" />
			<Method name="getUpdatedAt" />
			<Method name="setUpdatedAt" />
		</Or>
	</Match>
	<Match>
		<!--
			String[] allowedContentTypes: potentially caller can modify data after passing it to the
			constructor. I don't want to fix it because all such places are known and under our
			control.
		-->
		<Class name="ru.mystamps.web.feature.series.HttpURLConnectionDownloaderService" />
		<Bug pattern="EI_EXPOSE_REP2" />
	</Match>
	<Match>
		<!--
			DTO class exposes its internal representation and it's ok to me.
		-->
		<Class name="ru.mystamps.web.feature.series.DownloadResult" />
		<Bug pattern="EI_EXPOSE_REP" />
	</Match>
	<Match>
		<!--
			It's ok, that we're don't override parent's equals() method.
		-->
		<Class name="ru.mystamps.web.support.spring.security.CustomUserDetails" />
		<Bug pattern="EQ_DOESNT_OVERRIDE_EQUALS" />
	</Match>
	<Match>
		<!--
			I don't care about a serialVersionUID field.
		-->
		<Bug pattern="SE_NO_SERIALVERSIONID" />
	</Match>
	<Match>
		<!--
			Looks like a false positive.
		-->
		<Class name="ru.mystamps.web.feature.series.importing.extractor.JsoupSiteParserTest" />
		<Method name="canParseShouldRequireNonNullUrl" />
		<Bug pattern="NP_NULL_PARAM_DEREF_ALL_TARGETS_DANGEROUS" />
	</Match>
	<Match>
		<!--
			No one should assign a value returned from this method to primitive boolean type.
		-->
		<Class name="ru.mystamps.web.common.JdbcUtils" />
		<Method name="getBoolean" />
		<Bug pattern="NP_BOOLEAN_RETURN_NULL" />
	</Match>
	<Match>
		<!-- I hope that JdbcTemplate.update() method won't modify the list of generated keys -->
		<Class name="ru.mystamps.web.common.JdbcUtils" />
		<Bug pattern="MS_MUTABLE_ARRAY" />
	</Match>
	<Match>
		<!--
			No one should assign a value returned from this method to primitive boolean type.
		-->
		<Class name="ru.mystamps.web.feature.series.importing.SeriesInfoExtractorServiceImpl" />
		<Method name="extractPerforated" />
		<Bug pattern="NP_BOOLEAN_RETURN_NULL" />
	</Match>
	<Match>
		<!-- @todo #493 AddCategoryDbDto: port to a new datetime API -->
		<Class name="ru.mystamps.web.feature.category.AddCategoryDbDto" />
		<Or>
			<Method name="getCreatedAt" />
			<Method name="setCreatedAt" />
			<Method name="getUpdatedAt" />
			<Method name="setUpdatedAt" />
		</Or>
		<Bug pattern="EI_EXPOSE_REP,EI_EXPOSE_REP2" />
	</Match>
	<Match>
		<!-- @todo #493 AddCountryDbDto: port to a new datetime API -->
		<Class name="ru.mystamps.web.feature.country.AddCountryDbDto" />
		<Or>
			<Method name="getCreatedAt" />
			<Method name="setCreatedAt" />
			<Method name="getUpdatedAt" />
			<Method name="setUpdatedAt" />
		</Or>
		<Bug pattern="EI_EXPOSE_REP,EI_EXPOSE_REP2" />
	</Match>
	<Match>
		<!-- @todo #493 AddCollectionDbDto: port to a new datetime API -->
		<Class name="ru.mystamps.web.feature.collection.AddCollectionDbDto" />
		<Or>
			<Method name="getUpdatedAt" />
			<Method name="setUpdatedAt" />
		</Or>
		<Bug pattern="EI_EXPOSE_REP,EI_EXPOSE_REP2" />
	</Match>
	<Match>
		<!-- @todo #493 AddSuspiciousActivityDbDto: port to a new datetime API -->
		<Class name="ru.mystamps.web.feature.site.AddSuspiciousActivityDbDto" />
		<Bug pattern="EI_EXPOSE_REP,EI_EXPOSE_REP2" />
	</Match>
	<Match>
		<!-- @todo #493 SuspiciousActivityDto: port to a new datetime API -->
		<Class name="ru.mystamps.web.feature.site.SuspiciousActivityDto" />
		<Bug pattern="EI_EXPOSE_REP,EI_EXPOSE_REP2" />
	</Match>
	
</FindBugsFilter>
