<beans xmlns="http://www.springframework.org/schema/beans"
	xmlns:xsi="http://www.w3.org/2001/XMLSchema-instance"
	xmlns:context="http://www.springframework.org/schema/context"
	xmlns:tx="http://www.springframework.org/schema/tx"
	xsi:schemaLocation="http://www.springframework.org/schema/beans
	http://www.springframework.org/schema/beans/spring-beans-3.0.xsd
	http://www.springframework.org/schema/context
	http://www.springframework.org/schema/context/spring-context-3.0.xsd
	http://www.springframework.org/schema/tx
	http://www.springframework.org/schema/tx/spring-tx-3.0.xsd">
	
	<tx:annotation-driven />
	
	<context:property-placeholder location="classpath:spring/database.properties" />
	
	<import resource="datasource.xml" />
	
	<bean id="jpaVendorAdapter"
		class="org.springframework.orm.jpa.vendor.HibernateJpaVendorAdapter">
		<property name="databasePlatform" value="${jpa.dialectClassName}" />
		<property name="showSql" value="${jpa.showSql}" />
	</bean>
	
	<bean id="entityManagerFactory"
		class="org.springframework.orm.jpa.LocalContainerEntityManagerFactoryBean">
		<property name="jpaVendorAdapter">
			<ref local="jpaVendorAdapter" />
		</property>
		<property name="dataSource" ref="dataSource" />
		<property name="jpaProperties">
			<props>
				<prop key="hibernate.format_sql">${hibernate.formatSql}</prop>
				<prop key="hibernate.connection.charset">UTF-8</prop>
				<prop key="hibernate.hbm2ddl.auto">${hibernate.hbm2ddl.auto}</prop>
			</props>
		</property>
	</bean>
	
	<bean id="transactionManager"
		class="org.springframework.orm.jpa.JpaTransactionManager">
		<property name="entityManagerFactory">
			<ref local="entityManagerFactory" />
		</property>
	</bean>
	
	<!-- enable injection of EntityManager to beans with @PersistenceContext annotation -->
	<bean class="org.springframework.orm.jpa.support.PersistenceAnnotationBeanPostProcessor" />
	
</beans>
